syncd/_tracker.py
syncd/_devices.py
syncd/__main__.py
syncd/__init__.py
syncd/_executable.py
syncd/_concurrent.py
syncd/_request.py
syncd/py.typed
syncd/_cli.py
syncd-0.2.0.dist-info/WHEEL
syncd-0.2.0.dist-info/entry_points.txt
syncd-0.2.0.dist-info/METADATA
syncd-0.2.0.dist-info/RECORD
