Metadata-Version: 2.3
Name: syncd
Version: 0.2.0
Summary: CLI tool to synchronize directories using rsync.
Author: Christian Heinze
Classifier: Development Status :: 3 - Alpha
Classifier: Environment :: Console
Classifier: License :: OSI Approved :: Apache Software License
Classifier: Operating System :: POSIX :: Linux
Classifier: Programming Language :: Python :: 3 :: Only
Classifier: Programming Language :: Python :: 3.12
Classifier: Topic :: Utilities
Classifier: Typing :: Typed
Requires-Dist: aiosqlite>=0.21
Requires-Dist: pydantic>=2.10
Requires-Dist: rich>=13.9
Requires-Python: >=3.12
Project-URL: Repository, https://codeberg.org/christianheinze/syncd
